ytwrapper/__init__.py
ytwrapper/client.py
ytwrapper/apis/ChannelSections.py
ytwrapper/apis/Channels.py
ytwrapper/apis/CommentThreads.py
ytwrapper/apis/Comments.py
ytwrapper/apis/I18ns.py
ytwrapper/apis/PlaylistItems.py
ytwrapper/apis/Playlists.py
ytwrapper/apis/Searches.py
ytwrapper/apis/Subscriptions.py
ytwrapper/apis/Thumbnails.py
ytwrapper/apis/VideoExtras.py
ytwrapper/apis/Videos.py
ytwrapper/apis/__init__.py
ytwrapper/resources/ChannelResources.py
ytwrapper/resources/ChannelSectionResources.py
ytwrapper/resources/CommentResources.py
ytwrapper/resources/CommentThreadResources.py
ytwrapper/resources/I18nResources.py
ytwrapper/resources/PlaylistItemResources.py
ytwrapper/resources/PlaylistResources.py
ytwrapper/resources/SearchResultResources.py
ytwrapper/resources/SubscriptionResources.py
ytwrapper/resources/ThumbnailResources.py
ytwrapper/resources/VideoExtraResources.py
ytwrapper/resources/VideoResources.py
ytwrapper/resources/__init__.py
ytwrapper/resources/utils.py
yt_wrapper-0.2.1.dist-info/LICENSE
yt_wrapper-0.2.1.dist-info/METADATA
yt_wrapper-0.2.1.dist-info/WHEEL
yt_wrapper-0.2.1.dist-info/top_level.txt
yt_wrapper-0.2.1.dist-info/RECORD
