Metadata-Version: 2.1
Name: yt-wrapper
Version: 0.2.1
Summary: A simple wrapper around the Youtube Data API.
Home-page: https://github.com/Robert-Phan/yt-wrapper
Author: Robert Phan
Author-email: fannk987@gmail.com
License: MIT
Platform: UNKNOWN
Classifier: Programming Language :: Python :: 3
Classifier: Development Status :: 3 - Alpha
Classifier: License :: OSI Approved :: MIT License
License-File: LICENSE
Requires-Dist: google-api-python-client (>=2)
Requires-Dist: google-auth-oauthlib (>=0.4)
Requires-Dist: google-auth-httplib2 (>=0.1)
